ledapy/__init__.py
ledapy/analyse.py
ledapy/deconvolution.py
ledapy/leda2.py
ledapy/runner.py
ledapy/setup.py
ledapy/snips.py
ledapy/utils.py
ledapy-1.2.dist-info/LICENSE
ledapy-1.2.dist-info/METADATA
ledapy-1.2.dist-info/WHEEL
ledapy-1.2.dist-info/top_level.txt
ledapy-1.2.dist-info/RECORD
