Metadata-Version: 2.1
Name: ledapy
Version: 1.2
Summary: Ledapy is a minimal port of Ledalab (www.ledalab.de) for Python
Home-page: https://github.com/HIIT/ledapy
Author: Marco Filetti
Author-email: UNKNOWN
License: UNKNOWN
Platform: UNKNOWN
Classifier: Programming Language :: Python :: 3
Classifier: License :: OSI Approved :: MIT License
Classifier: Operating System :: OS Independent
Requires-Dist: numpy
Requires-Dist: scipy
Requires-Dist: sympy
